{"totalProprietaryEntriesWithUPCs": 3850, "totalGenericEntries": 877, "averageNewBarcodes": 86, "totalEntries": 6851, "weeksForAverages": 18, "grandTotalProprietaryEntries": 5614, "averageNewEntries": 65, "totalPosstubEntries": 612, "totalAbstractEntries": 46, "totalBrandEntries": 205, "percentageProprietaryEntriesWithUPCs": 70, "totalWeakcatEntries": 61, "totalStubEntries": 4451, "grandTotalUPCs": 8222, "totalProprietaryEntries": 551, "totalPOSCodeUPCs": 3377, "totalAdhocEntries": 33, "totalUserUPCs": 4845}